[{ "date": "1360224000000", "type": "meeting", "title": "Test Last Year", "description": "Lorem Ipsum dolor set"},{ "date": "1360828800000", "type": "meeting", "title": "Test Last Year", "description": "Lorem Ipsum dolor set"},{ "date": "1361520000000", "type": "meeting", "title": "Test Last Year", "description": "Lorem Ipsum dolor set"},{ "date": "1361779200000", "type": "meeting", "title": "Test Last Year", "description": "Lorem Ipsum dolor set"},{ "date": "1363158000000", "type": "meeting", "title": "Test Last Year", "description": "Lorem Ipsum dolor set"},{ "date": "1360915200000", "type": "meeting", "title": "Test Last Year", "description": "Lorem Ipsum dolor set"},{ "date": "1361952000000", "type": "meeting", "title": "Test Last Year", "description": "Lorem Ipsum dolor set"},{ "date": "1366873200000", "type": "meeting", "title": "Test Last Year", "description": "Lorem Ipsum dolor set"},{ "date": "1367305200000", "type": "meeting", "title": "Test Last Year", "description": "Lorem Ipsum dolor set"},{ "date": "1364626800000", "type": "meeting", "title": "Test Last Year", "description": "Lorem Ipsum dolor set"}]